metaflow_extensions/pyspark/plugins/__init__.py
metaflow_extensions/pyspark/plugins/metaflow_pyspark.py
metaflow_extensions/pyspark/plugins/pyspark_driver.py
metaflow_pyspark-0.0.2.dist-info/LICENSE
metaflow_pyspark-0.0.2.dist-info/METADATA
metaflow_pyspark-0.0.2.dist-info/WHEEL
metaflow_pyspark-0.0.2.dist-info/top_level.txt
metaflow_pyspark-0.0.2.dist-info/RECORD
