Metadata-Version: 2.1
Name: metaflow-pyspark
Version: 0.0.2
Summary: An EXPERIMENTAL PySpark decorator for Metaflow
Author: Ville Tuulos
Author-email: ville@outerbounds.co
License-File: LICENSE
Requires-Dist: metaflow
